ogham/__init__.py
ogham/mappings.py
ogham-1.0.0.dist-info/LICENSE
ogham-1.0.0.dist-info/METADATA
ogham-1.0.0.dist-info/WHEEL
ogham-1.0.0.dist-info/top_level.txt
ogham-1.0.0.dist-info/RECORD
