Metadata-Version: 2.1
Name: ogham
Version: 1.0.0
Summary: Convert Ogham inscriptions to latin text & vice versa.
Home-page: https://github.com/stscoundrel/ogham-py
Author: stscoundrel
License: UNKNOWN
Platform: UNKNOWN
Requires-Python: >=3.9
License-File: LICENSE
